[
  {
    "etf_code": "0050",
    "etf_name": "元大台灣50",
    "stock_code": "2330",
    "stock_name": "台積電",
    "weight": 58.65,
    "shares": 529987680,
    "data_date": "2026-07-07",
    "source": "auto",
    "source_url": "https://www.yuantaetfs.com/product/detail/0050/ratio"
  },
  {
    "etf_code": "0050",
    "etf_name": "元大台灣50",
    "stock_code": "2454",
    "stock_name": "聯發科",
    "weight": 5.85,
    "shares": 32023257,
    "data_date": "2026-07-07",
    "source": "auto",
    "source_url": "https://www.yuantaetfs.com/product/detail/0050/ratio"
  },
  {
    "etf_code": "0050",
    "etf_name": "元大台灣50",
    "stock_code": "2308",
    "stock_name": "台達電",
    "weight": 3.59,
    "shares": 41901974,
    "data_date": "2026-07-07",
    "source": "auto",
    "source_url": "https://www.yuantaetfs.com/product/detail/0050/ratio"
  },
  {
    "etf_code": "0050",
    "etf_name": "元大台灣50",
    "stock_code": "2317",
    "stock_name": "鴻海",
    "weight": 2.85,
    "shares": 264773919,
    "data_date": "2026-07-07",
    "source": "auto",
    "source_url": "https://www.yuantaetfs.com/product/detail/0050/ratio"
  },
  {
    "etf_code": "0050",
    "etf_name": "元大台灣50",
    "stock_code": "3711",
    "stock_name": "日月光投控",
    "weight": 2.13,
    "shares": 72017628,
    "data_date": "2026-07-07",
    "source": "auto",
    "source_url": "https://www.yuantaetfs.com/product/detail/0050/ratio"
  },
  {
    "etf_code": "0050",
    "etf_name": "元大台灣50",
    "stock_code": "2303",
    "stock_name": "聯電",
    "weight": 1.78,
    "shares": 253431991,
    "data_date": "2026-07-07",
    "source": "auto",
    "source_url": "https://www.yuantaetfs.com/product/detail/0050/ratio"
  },
  {
    "etf_code": "0050",
    "etf_name": "元大台灣50",
    "stock_code": "2383",
    "stock_name": "台光電",
    "weight": 1.49,
    "shares": 6310949,
    "data_date": "2026-07-07",
    "source": "auto",
    "source_url": "https://www.yuantaetfs.com/product/detail/0050/ratio"
  },
  {
    "etf_code": "0050",
    "etf_name": "元大台灣50",
    "stock_code": "2327",
    "stock_name": "國巨*",
    "weight": 1.4,
    "shares": 34207023,
    "data_date": "2026-07-07",
    "source": "auto",
    "source_url": "https://www.yuantaetfs.com/product/detail/0050/ratio"
  },
  {
    "etf_code": "0050",
    "etf_name": "元大台灣50",
    "stock_code": "2891",
    "stock_name": "中信金",
    "weight": 1.23,
    "shares": 385212593,
    "data_date": "2026-07-07",
    "source": "auto",
    "source_url": "https://www.yuantaetfs.com/product/detail/0050/ratio"
  },
  {
    "etf_code": "0050",
    "etf_name": "元大台灣50",
    "stock_code": "2345",
    "stock_name": "智邦",
    "weight": 1.2,
    "shares": 10801507,
    "data_date": "2026-07-07",
    "source": "auto",
    "source_url": "https://www.yuantaetfs.com/product/detail/0050/ratio"
  },
  {
    "etf_code": "0050",
    "etf_name": "元大台灣50",
    "stock_code": "3037",
    "stock_name": "欣興",
    "weight": 1.09,
    "shares": 28605672,
    "data_date": "2026-07-07",
    "source": "auto",
    "source_url": "https://www.yuantaetfs.com/product/detail/0050/ratio"
  },
  {
    "etf_code": "0050",
    "etf_name": "元大台灣50",
    "stock_code": "2881",
    "stock_name": "富邦金",
    "weight": 1.01,
    "shares": 180647032,
    "data_date": "2026-07-07",
    "source": "auto",
    "source_url": "https://www.yuantaetfs.com/product/detail/0050/ratio"
  },
  {
    "etf_code": "0050",
    "etf_name": "元大台灣50",
    "stock_code": "2382",
    "stock_name": "廣達",
    "weight": 0.97,
    "shares": 57248617,
    "data_date": "2026-07-07",
    "source": "auto",
    "source_url": "https://www.yuantaetfs.com/product/detail/0050/ratio"
  },
  {
    "etf_code": "0050",
    "etf_name": "元大台灣50",
    "stock_code": "2882",
    "stock_name": "國泰金",
    "weight": 0.91,
    "shares": 206563859,
    "data_date": "2026-07-07",
    "source": "auto",
    "source_url": "https://www.yuantaetfs.com/product/detail/0050/ratio"
  },
  {
    "etf_code": "0050",
    "etf_name": "元大台灣50",
    "stock_code": "1303",
    "stock_name": "南亞",
    "weight": 0.81,
    "shares": 106967170,
    "data_date": "2026-07-07",
    "source": "auto",
    "source_url": "https://www.yuantaetfs.com/product/detail/0050/ratio"
  },
  {
    "etf_code": "0050",
    "etf_name": "元大台灣50",
    "stock_code": "2887",
    "stock_name": "台新新光金",
    "weight": 0.8,
    "shares": 502511420,
    "data_date": "2026-07-07",
    "source": "auto",
    "source_url": "https://www.yuantaetfs.com/product/detail/0050/ratio"
  },
  {
    "etf_code": "0050",
    "etf_name": "元大台灣50",
    "stock_code": "3017",
    "stock_name": "奇鋐",
    "weight": 0.77,
    "shares": 6931610,
    "data_date": "2026-07-07",
    "source": "auto",
    "source_url": "https://www.yuantaetfs.com/product/detail/0050/ratio"
  },
  {
    "etf_code": "0050",
    "etf_name": "元大台灣50",
    "stock_code": "2885",
    "stock_name": "元大金",
    "weight": 0.76,
    "shares": 239087328,
    "data_date": "2026-07-07",
    "source": "auto",
    "source_url": "https://www.yuantaetfs.com/product/detail/0050/ratio"
  },
  {
    "etf_code": "0050",
    "etf_name": "元大台灣50",
    "stock_code": "2360",
    "stock_name": "致茂",
    "weight": 0.71,
    "shares": 7982923,
    "data_date": "2026-07-07",
    "source": "auto",
    "source_url": "https://www.yuantaetfs.com/product/detail/0050/ratio"
  },
  {
    "etf_code": "0050",
    "etf_name": "元大台灣50",
    "stock_code": "2886",
    "stock_name": "兆豐金",
    "weight": 0.54,
    "shares": 255975391,
    "data_date": "2026-07-07",
    "source": "auto",
    "source_url": "https://www.yuantaetfs.com/product/detail/0050/ratio"
  },
  {
    "etf_code": "0050",
    "etf_name": "元大台灣50",
    "stock_code": "2344",
    "stock_name": "華邦電",
    "weight": 0.53,
    "shares": 66998023,
    "data_date": "2026-07-07",
    "source": "auto",
    "source_url": "https://www.yuantaetfs.com/product/detail/0050/ratio"
  },
  {
    "etf_code": "0050",
    "etf_name": "元大台灣50",
    "stock_code": "2412",
    "stock_name": "中華電",
    "weight": 0.53,
    "shares": 82481236,
    "data_date": "2026-07-07",
    "source": "auto",
    "source_url": "https://www.yuantaetfs.com/product/detail/0050/ratio"
  },
  {
    "etf_code": "0050",
    "etf_name": "元大台灣50",
    "stock_code": "2884",
    "stock_name": "玉山金",
    "weight": 0.52,
    "shares": 329236041,
    "data_date": "2026-07-07",
    "source": "auto",
    "source_url": "https://www.yuantaetfs.com/product/detail/0050/ratio"
  },
  {
    "etf_code": "0050",
    "etf_name": "元大台灣50",
    "stock_code": "2890",
    "stock_name": "永豐金",
    "weight": 0.52,
    "shares": 278245966,
    "data_date": "2026-07-07",
    "source": "auto",
    "source_url": "https://www.yuantaetfs.com/product/detail/0050/ratio"
  },
  {
    "etf_code": "0050",
    "etf_name": "元大台灣50",
    "stock_code": "6669",
    "stock_name": "緯穎",
    "weight": 0.51,
    "shares": 2250962,
    "data_date": "2026-07-07",
    "source": "auto",
    "source_url": "https://www.yuantaetfs.com/product/detail/0050/ratio"
  },
  {
    "etf_code": "0050",
    "etf_name": "元大台灣50",
    "stock_code": "2883",
    "stock_name": "凱基金",
    "weight": 0.47,
    "shares": 341108348,
    "data_date": "2026-07-07",
    "source": "auto",
    "source_url": "https://www.yuantaetfs.com/product/detail/0050/ratio"
  },
  {
    "etf_code": "0050",
    "etf_name": "元大台灣50",
    "stock_code": "3231",
    "stock_name": "緯創",
    "weight": 0.46,
    "shares": 65396958,
    "data_date": "2026-07-07",
    "source": "auto",
    "source_url": "https://www.yuantaetfs.com/product/detail/0050/ratio"
  },
  {
    "etf_code": "0050",
    "etf_name": "元大台灣50",
    "stock_code": "2059",
    "stock_name": "川湖",
    "weight": 0.45,
    "shares": 1194040,
    "data_date": "2026-07-07",
    "source": "auto",
    "source_url": "https://www.yuantaetfs.com/product/detail/0050/ratio"
  },
  {
    "etf_code": "0050",
    "etf_name": "元大台灣50",
    "stock_code": "2408",
    "stock_name": "南亞科",
    "weight": 0.45,
    "shares": 24706816,
    "data_date": "2026-07-07",
    "source": "auto",
    "source_url": "https://www.yuantaetfs.com/product/detail/0050/ratio"
  },
  {
    "etf_code": "0050",
    "etf_name": "元大台灣50",
    "stock_code": "2357",
    "stock_name": "華碩",
    "weight": 0.44,
    "shares": 14616596,
    "data_date": "2026-07-07",
    "source": "auto",
    "source_url": "https://www.yuantaetfs.com/product/detail/0050/ratio"
  },
  {
    "etf_code": "0050",
    "etf_name": "元大台灣50",
    "stock_code": "2301",
    "stock_name": "光寶科",
    "weight": 0.41,
    "shares": 42363274,
    "data_date": "2026-07-07",
    "source": "auto",
    "source_url": "https://www.yuantaetfs.com/product/detail/0050/ratio"
  },
  {
    "etf_code": "0050",
    "etf_name": "元大台灣50",
    "stock_code": "4958",
    "stock_name": "臻鼎-KY",
    "weight": 0.41,
    "shares": 16515455,
    "data_date": "2026-07-07",
    "source": "auto",
    "source_url": "https://www.yuantaetfs.com/product/detail/0050/ratio"
  },
  {
    "etf_code": "0050",
    "etf_name": "元大台灣50",
    "stock_code": "1216",
    "stock_name": "統一",
    "weight": 0.38,
    "shares": 107018062,
    "data_date": "2026-07-07",
    "source": "auto",
    "source_url": "https://www.yuantaetfs.com/product/detail/0050/ratio"
  },
  {
    "etf_code": "0050",
    "etf_name": "元大台灣50",
    "stock_code": "2368",
    "stock_name": "金像電",
    "weight": 0.38,
    "shares": 7443844,
    "data_date": "2026-07-07",
    "source": "auto",
    "source_url": "https://www.yuantaetfs.com/product/detail/0050/ratio"
  },
  {
    "etf_code": "0050",
    "etf_name": "元大台灣50",
    "stock_code": "2892",
    "stock_name": "第一金",
    "weight": 0.37,
    "shares": 242559797,
    "data_date": "2026-07-07",
    "source": "auto",
    "source_url": "https://www.yuantaetfs.com/product/detail/0050/ratio"
  },
  {
    "etf_code": "0050",
    "etf_name": "元大台灣50",
    "stock_code": "3008",
    "stock_name": "大立光",
    "weight": 0.36,
    "shares": 2033253,
    "data_date": "2026-07-07",
    "source": "auto",
    "source_url": "https://www.yuantaetfs.com/product/detail/0050/ratio"
  },
  {
    "etf_code": "0050",
    "etf_name": "元大台灣50",
    "stock_code": "2880",
    "stock_name": "華南金",
    "weight": 0.35,
    "shares": 199096505,
    "data_date": "2026-07-07",
    "source": "auto",
    "source_url": "https://www.yuantaetfs.com/product/detail/0050/ratio"
  },
  {
    "etf_code": "0050",
    "etf_name": "元大台灣50",
    "stock_code": "3443",
    "stock_name": "創意",
    "weight": 0.35,
    "shares": 1739734,
    "data_date": "2026-07-07",
    "source": "auto",
    "source_url": "https://www.yuantaetfs.com/product/detail/0050/ratio"
  },
  {
    "etf_code": "0050",
    "etf_name": "元大台灣50",
    "stock_code": "3665",
    "stock_name": "貿聯-KY",
    "weight": 0.35,
    "shares": 3871911,
    "data_date": "2026-07-07",
    "source": "auto",
    "source_url": "https://www.yuantaetfs.com/product/detail/0050/ratio"
  },
  {
    "etf_code": "0050",
    "etf_name": "元大台灣50",
    "stock_code": "7769",
    "stock_name": "鴻勁",
    "weight": 0.35,
    "shares": 1235033,
    "data_date": "2026-07-07",
    "source": "auto",
    "source_url": "https://www.yuantaetfs.com/product/detail/0050/ratio"
  },
  {
    "etf_code": "0050",
    "etf_name": "元大台灣50",
    "stock_code": "2449",
    "stock_name": "京元電子",
    "weight": 0.34,
    "shares": 23548406,
    "data_date": "2026-07-07",
    "source": "auto",
    "source_url": "https://www.yuantaetfs.com/product/detail/0050/ratio"
  },
  {
    "etf_code": "0050",
    "etf_name": "元大台灣50",
    "stock_code": "3661",
    "stock_name": "世芯-KY",
    "weight": 0.31,
    "shares": 1708433,
    "data_date": "2026-07-07",
    "source": "auto",
    "source_url": "https://www.yuantaetfs.com/product/detail/0050/ratio"
  },
  {
    "etf_code": "0050",
    "etf_name": "元大台灣50",
    "stock_code": "3653",
    "stock_name": "健策",
    "weight": 0.27,
    "shares": 1886810,
    "data_date": "2026-07-07",
    "source": "auto",
    "source_url": "https://www.yuantaetfs.com/product/detail/0050/ratio"
  },
  {
    "etf_code": "0050",
    "etf_name": "元大台灣50",
    "stock_code": "5880",
    "stock_name": "合庫金",
    "weight": 0.26,
    "shares": 226718295,
    "data_date": "2026-07-07",
    "source": "auto",
    "source_url": "https://www.yuantaetfs.com/product/detail/0050/ratio"
  },
  {
    "etf_code": "0050",
    "etf_name": "元大台灣50",
    "stock_code": "2395",
    "stock_name": "研華",
    "weight": 0.22,
    "shares": 9985154,
    "data_date": "2026-07-07",
    "source": "auto",
    "source_url": "https://www.yuantaetfs.com/product/detail/0050/ratio"
  },
  {
    "etf_code": "0050",
    "etf_name": "元大台灣50",
    "stock_code": "8046",
    "stock_name": "南電",
    "weight": 0.22,
    "shares": 4638624,
    "data_date": "2026-07-07",
    "source": "auto",
    "source_url": "https://www.yuantaetfs.com/product/detail/0050/ratio"
  },
  {
    "etf_code": "0050",
    "etf_name": "元大台灣50",
    "stock_code": "2603",
    "stock_name": "長榮",
    "weight": 0.2,
    "shares": 23527209,
    "data_date": "2026-07-07",
    "source": "auto",
    "source_url": "https://www.yuantaetfs.com/product/detail/0050/ratio"
  },
  {
    "etf_code": "0050",
    "etf_name": "元大台灣50",
    "stock_code": "4904",
    "stock_name": "遠傳",
    "weight": 0.18,
    "shares": 38226740,
    "data_date": "2026-07-07",
    "source": "auto",
    "source_url": "https://www.yuantaetfs.com/product/detail/0050/ratio"
  },
  {
    "etf_code": "0050",
    "etf_name": "元大台灣50",
    "stock_code": "3045",
    "stock_name": "台灣大",
    "weight": 0.16,
    "shares": 30441240,
    "data_date": "2026-07-07",
    "source": "auto",
    "source_url": "https://www.yuantaetfs.com/product/detail/0050/ratio"
  },
  {
    "etf_code": "0050",
    "etf_name": "元大台灣50",
    "stock_code": "6505",
    "stock_name": "台塑化",
    "weight": 0.07,
    "shares": 24848880,
    "data_date": "2026-07-07",
    "source": "auto",
    "source_url": "https://www.yuantaetfs.com/product/detail/0050/ratio"
  },
  {
    "etf_code": "0056",
    "etf_name": "元大高股息",
    "stock_code": "2382",
    "stock_name": "廣達",
    "weight": 4.46,
    "shares": 85223729,
    "data_date": "2026-07-07",
    "source": "auto",
    "source_url": "https://www.yuantaetfs.com/product/detail/0056/ratio"
  },
  {
    "etf_code": "0056",
    "etf_name": "元大高股息",
    "stock_code": "2891",
    "stock_name": "中信金",
    "weight": 4.36,
    "shares": 442620190,
    "data_date": "2026-07-07",
    "source": "auto",
    "source_url": "https://www.yuantaetfs.com/product/detail/0056/ratio"
  },
  {
    "etf_code": "0056",
    "etf_name": "元大高股息",
    "stock_code": "2344",
    "stock_name": "華邦電",
    "weight": 4.14,
    "shares": 169404581,
    "data_date": "2026-07-07",
    "source": "auto",
    "source_url": "https://www.yuantaetfs.com/product/detail/0056/ratio"
  },
  {
    "etf_code": "0056",
    "etf_name": "元大高股息",
    "stock_code": "2890",
    "stock_name": "永豐金",
    "weight": 4.06,
    "shares": 702824671,
    "data_date": "2026-07-07",
    "source": "auto",
    "source_url": "https://www.yuantaetfs.com/product/detail/0056/ratio"
  },
  {
    "etf_code": "0056",
    "etf_name": "元大高股息",
    "stock_code": "2408",
    "stock_name": "南亞科",
    "weight": 3.75,
    "shares": 66239423,
    "data_date": "2026-07-07",
    "source": "auto",
    "source_url": "https://www.yuantaetfs.com/product/detail/0056/ratio"
  },
  {
    "etf_code": "0056",
    "etf_name": "元大高股息",
    "stock_code": "2880",
    "stock_name": "華南金",
    "weight": 3.7,
    "shares": 677039503,
    "data_date": "2026-07-07",
    "source": "auto",
    "source_url": "https://www.yuantaetfs.com/product/detail/0056/ratio"
  },
  {
    "etf_code": "0056",
    "etf_name": "元大高股息",
    "stock_code": "2886",
    "stock_name": "兆豐金",
    "weight": 3.51,
    "shares": 533816544,
    "data_date": "2026-07-07",
    "source": "auto",
    "source_url": "https://www.yuantaetfs.com/product/detail/0056/ratio"
  },
  {
    "etf_code": "0056",
    "etf_name": "元大高股息",
    "stock_code": "2303",
    "stock_name": "聯電",
    "weight": 3.5,
    "shares": 160606427,
    "data_date": "2026-07-07",
    "source": "auto",
    "source_url": "https://www.yuantaetfs.com/product/detail/0056/ratio"
  },
  {
    "etf_code": "0056",
    "etf_name": "元大高股息",
    "stock_code": "3231",
    "stock_name": "緯創",
    "weight": 3.49,
    "shares": 159820143,
    "data_date": "2026-07-07",
    "source": "auto",
    "source_url": "https://www.yuantaetfs.com/product/detail/0056/ratio"
  },
  {
    "etf_code": "0056",
    "etf_name": "元大高股息",
    "stock_code": "2357",
    "stock_name": "華碩",
    "weight": 3.16,
    "shares": 33968300,
    "data_date": "2026-07-07",
    "source": "auto",
    "source_url": "https://www.yuantaetfs.com/product/detail/0056/ratio"
  },
  {
    "etf_code": "0056",
    "etf_name": "元大高股息",
    "stock_code": "2885",
    "stock_name": "元大金",
    "weight": 2.83,
    "shares": 288608355,
    "data_date": "2026-07-07",
    "source": "auto",
    "source_url": "https://www.yuantaetfs.com/product/detail/0056/ratio"
  },
  {
    "etf_code": "0056",
    "etf_name": "元大高股息",
    "stock_code": "2379",
    "stock_name": "瑞昱",
    "weight": 2.74,
    "shares": 25096191,
    "data_date": "2026-07-07",
    "source": "auto",
    "source_url": "https://www.yuantaetfs.com/product/detail/0056/ratio"
  },
  {
    "etf_code": "0056",
    "etf_name": "元大高股息",
    "stock_code": "1216",
    "stock_name": "統一",
    "weight": 2.71,
    "shares": 247037322,
    "data_date": "2026-07-07",
    "source": "auto",
    "source_url": "https://www.yuantaetfs.com/product/detail/0056/ratio"
  },
  {
    "etf_code": "0056",
    "etf_name": "元大高股息",
    "stock_code": "1303",
    "stock_name": "南亞",
    "weight": 2.67,
    "shares": 114308955,
    "data_date": "2026-07-07",
    "source": "auto",
    "source_url": "https://www.yuantaetfs.com/product/detail/0056/ratio"
  },
  {
    "etf_code": "0056",
    "etf_name": "元大高股息",
    "stock_code": "2883",
    "stock_name": "凱基金",
    "weight": 2.47,
    "shares": 583631418,
    "data_date": "2026-07-07",
    "source": "auto",
    "source_url": "https://www.yuantaetfs.com/product/detail/0056/ratio"
  },
  {
    "etf_code": "0056",
    "etf_name": "元大高股息",
    "stock_code": "2603",
    "stock_name": "長榮",
    "weight": 2.42,
    "shares": 91698464,
    "data_date": "2026-07-07",
    "source": "auto",
    "source_url": "https://www.yuantaetfs.com/product/detail/0056/ratio"
  },
  {
    "etf_code": "0056",
    "etf_name": "元大高股息",
    "stock_code": "3045",
    "stock_name": "台灣大",
    "weight": 2.28,
    "shares": 139563327,
    "data_date": "2026-07-07",
    "source": "auto",
    "source_url": "https://www.yuantaetfs.com/product/detail/0056/ratio"
  },
  {
    "etf_code": "0056",
    "etf_name": "元大高股息",
    "stock_code": "2317",
    "stock_name": "鴻海",
    "weight": 2.23,
    "shares": 66988514,
    "data_date": "2026-07-07",
    "source": "auto",
    "source_url": "https://www.yuantaetfs.com/product/detail/0056/ratio"
  },
  {
    "etf_code": "0056",
    "etf_name": "元大高股息",
    "stock_code": "2301",
    "stock_name": "光寶科",
    "weight": 2.2,
    "shares": 73513072,
    "data_date": "2026-07-07",
    "source": "auto",
    "source_url": "https://www.yuantaetfs.com/product/detail/0056/ratio"
  },
  {
    "etf_code": "0056",
    "etf_name": "元大高股息",
    "stock_code": "2887",
    "stock_name": "台新新光金",
    "weight": 2.17,
    "shares": 442780859,
    "data_date": "2026-07-07",
    "source": "auto",
    "source_url": "https://www.yuantaetfs.com/product/detail/0056/ratio"
  },
  {
    "etf_code": "0056",
    "etf_name": "元大高股息",
    "stock_code": "4904",
    "stock_name": "遠傳",
    "weight": 2.11,
    "shares": 145531592,
    "data_date": "2026-07-07",
    "source": "auto",
    "source_url": "https://www.yuantaetfs.com/product/detail/0056/ratio"
  },
  {
    "etf_code": "0056",
    "etf_name": "元大高股息",
    "stock_code": "3711",
    "stock_name": "日月光投控",
    "weight": 2.1,
    "shares": 22984485,
    "data_date": "2026-07-07",
    "source": "auto",
    "source_url": "https://www.yuantaetfs.com/product/detail/0056/ratio"
  },
  {
    "etf_code": "0056",
    "etf_name": "元大高股息",
    "stock_code": "3034",
    "stock_name": "聯詠",
    "weight": 2.09,
    "shares": 28005559,
    "data_date": "2026-07-07",
    "source": "auto",
    "source_url": "https://www.yuantaetfs.com/product/detail/0056/ratio"
  },
  {
    "etf_code": "0056",
    "etf_name": "元大高股息",
    "stock_code": "2884",
    "stock_name": "玉山金",
    "weight": 2.07,
    "shares": 426387953,
    "data_date": "2026-07-07",
    "source": "auto",
    "source_url": "https://www.yuantaetfs.com/product/detail/0056/ratio"
  },
  {
    "etf_code": "0056",
    "etf_name": "元大高股息",
    "stock_code": "2454",
    "stock_name": "聯發科",
    "weight": 1.88,
    "shares": 3329584,
    "data_date": "2026-07-07",
    "source": "auto",
    "source_url": "https://www.yuantaetfs.com/product/detail/0056/ratio"
  },
  {
    "etf_code": "0056",
    "etf_name": "元大高股息",
    "stock_code": "3036",
    "stock_name": "文曄",
    "weight": 1.85,
    "shares": 61709596,
    "data_date": "2026-07-07",
    "source": "auto",
    "source_url": "https://www.yuantaetfs.com/product/detail/0056/ratio"
  },
  {
    "etf_code": "0056",
    "etf_name": "元大高股息",
    "stock_code": "3044",
    "stock_name": "健鼎",
    "weight": 1.68,
    "shares": 25213895,
    "data_date": "2026-07-07",
    "source": "auto",
    "source_url": "https://www.yuantaetfs.com/product/detail/0056/ratio"
  },
  {
    "etf_code": "0056",
    "etf_name": "元大高股息",
    "stock_code": "6239",
    "stock_name": "力成",
    "weight": 1.61,
    "shares": 35405633,
    "data_date": "2026-07-07",
    "source": "auto",
    "source_url": "https://www.yuantaetfs.com/product/detail/0056/ratio"
  },
  {
    "etf_code": "0056",
    "etf_name": "元大高股息",
    "stock_code": "2356",
    "stock_name": "英業達",
    "weight": 1.48,
    "shares": 161098894,
    "data_date": "2026-07-07",
    "source": "auto",
    "source_url": "https://www.yuantaetfs.com/product/detail/0056/ratio"
  },
  {
    "etf_code": "0056",
    "etf_name": "元大高股息",
    "stock_code": "2618",
    "stock_name": "長榮航",
    "weight": 1.47,
    "shares": 247618539,
    "data_date": "2026-07-07",
    "source": "auto",
    "source_url": "https://www.yuantaetfs.com/product/detail/0056/ratio"
  },
  {
    "etf_code": "0056",
    "etf_name": "元大高股息",
    "stock_code": "2376",
    "stock_name": "技嘉",
    "weight": 1.44,
    "shares": 31308409,
    "data_date": "2026-07-07",
    "source": "auto",
    "source_url": "https://www.yuantaetfs.com/product/detail/0056/ratio"
  },
  {
    "etf_code": "0056",
    "etf_name": "元大高股息",
    "stock_code": "2449",
    "stock_name": "京元電子",
    "weight": 1.42,
    "shares": 31934436,
    "data_date": "2026-07-07",
    "source": "auto",
    "source_url": "https://www.yuantaetfs.com/product/detail/0056/ratio"
  },
  {
    "etf_code": "0056",
    "etf_name": "元大高股息",
    "stock_code": "4938",
    "stock_name": "和碩",
    "weight": 1.42,
    "shares": 122747976,
    "data_date": "2026-07-07",
    "source": "auto",
    "source_url": "https://www.yuantaetfs.com/product/detail/0056/ratio"
  },
  {
    "etf_code": "0056",
    "etf_name": "元大高股息",
    "stock_code": "5876",
    "stock_name": "上海商銀",
    "weight": 1.25,
    "shares": 210416693,
    "data_date": "2026-07-07",
    "source": "auto",
    "source_url": "https://www.yuantaetfs.com/product/detail/0056/ratio"
  },
  {
    "etf_code": "0056",
    "etf_name": "元大高股息",
    "stock_code": "3702",
    "stock_name": "大聯大",
    "weight": 1.15,
    "shares": 75017536,
    "data_date": "2026-07-07",
    "source": "auto",
    "source_url": "https://www.yuantaetfs.com/product/detail/0056/ratio"
  },
  {
    "etf_code": "0056",
    "etf_name": "元大高股息",
    "stock_code": "2347",
    "stock_name": "聯強",
    "weight": 1.03,
    "shares": 80247791,
    "data_date": "2026-07-07",
    "source": "auto",
    "source_url": "https://www.yuantaetfs.com/product/detail/0056/ratio"
  },
  {
    "etf_code": "0056",
    "etf_name": "元大高股息",
    "stock_code": "2324",
    "stock_name": "仁寶",
    "weight": 0.98,
    "shares": 197535212,
    "data_date": "2026-07-07",
    "source": "auto",
    "source_url": "https://www.yuantaetfs.com/product/detail/0056/ratio"
  },
  {
    "etf_code": "0056",
    "etf_name": "元大高股息",
    "stock_code": "6285",
    "stock_name": "啟碁",
    "weight": 0.78,
    "shares": 22799117,
    "data_date": "2026-07-07",
    "source": "auto",
    "source_url": "https://www.yuantaetfs.com/product/detail/0056/ratio"
  },
  {
    "etf_code": "0056",
    "etf_name": "元大高股息",
    "stock_code": "2377",
    "stock_name": "微星",
    "weight": 0.76,
    "shares": 39481652,
    "data_date": "2026-07-07",
    "source": "auto",
    "source_url": "https://www.yuantaetfs.com/product/detail/0056/ratio"
  },
  {
    "etf_code": "0056",
    "etf_name": "元大高股息",
    "stock_code": "1102",
    "stock_name": "亞泥",
    "weight": 0.74,
    "shares": 145582130,
    "data_date": "2026-07-07",
    "source": "auto",
    "source_url": "https://www.yuantaetfs.com/product/detail/0056/ratio"
  },
  {
    "etf_code": "0056",
    "etf_name": "元大高股息",
    "stock_code": "2474",
    "stock_name": "可成",
    "weight": 0.71,
    "shares": 25919224,
    "data_date": "2026-07-07",
    "source": "auto",
    "source_url": "https://www.yuantaetfs.com/product/detail/0056/ratio"
  },
  {
    "etf_code": "0056",
    "etf_name": "元大高股息",
    "stock_code": "2105",
    "stock_name": "正新",
    "weight": 0.67,
    "shares": 147744042,
    "data_date": "2026-07-07",
    "source": "auto",
    "source_url": "https://www.yuantaetfs.com/product/detail/0056/ratio"
  },
  {
    "etf_code": "0056",
    "etf_name": "元大高股息",
    "stock_code": "2027",
    "stock_name": "大成鋼",
    "weight": 0.6,
    "shares": 104787232,
    "data_date": "2026-07-07",
    "source": "auto",
    "source_url": "https://www.yuantaetfs.com/product/detail/0056/ratio"
  },
  {
    "etf_code": "0056",
    "etf_name": "元大高股息",
    "stock_code": "2353",
    "stock_name": "宏碁",
    "weight": 0.6,
    "shares": 134040059,
    "data_date": "2026-07-07",
    "source": "auto",
    "source_url": "https://www.yuantaetfs.com/product/detail/0056/ratio"
  },
  {
    "etf_code": "0056",
    "etf_name": "元大高股息",
    "stock_code": "1513",
    "stock_name": "中興電",
    "weight": 0.57,
    "shares": 23074211,
    "data_date": "2026-07-07",
    "source": "auto",
    "source_url": "https://www.yuantaetfs.com/product/detail/0056/ratio"
  },
  {
    "etf_code": "0056",
    "etf_name": "元大高股息",
    "stock_code": "2385",
    "stock_name": "群光",
    "weight": 0.5,
    "shares": 33432523,
    "data_date": "2026-07-07",
    "source": "auto",
    "source_url": "https://www.yuantaetfs.com/product/detail/0056/ratio"
  },
  {
    "etf_code": "0056",
    "etf_name": "元大高股息",
    "stock_code": "3023",
    "stock_name": "信邦",
    "weight": 0.5,
    "shares": 11018663,
    "data_date": "2026-07-07",
    "source": "auto",
    "source_url": "https://www.yuantaetfs.com/product/detail/0056/ratio"
  },
  {
    "etf_code": "0056",
    "etf_name": "元大高股息",
    "stock_code": "3005",
    "stock_name": "神基",
    "weight": 0.44,
    "shares": 29104194,
    "data_date": "2026-07-07",
    "source": "auto",
    "source_url": "https://www.yuantaetfs.com/product/detail/0056/ratio"
  },
  {
    "etf_code": "0056",
    "etf_name": "元大高股息",
    "stock_code": "2645",
    "stock_name": "長榮航太",
    "weight": 0.41,
    "shares": 13457065,
    "data_date": "2026-07-07",
    "source": "auto",
    "source_url": "https://www.yuantaetfs.com/product/detail/0056/ratio"
  },
  {
    "etf_code": "0056",
    "etf_name": "元大高股息",
    "stock_code": "9904",
    "stock_name": "寶成",
    "weight": 0.37,
    "shares": 107712454,
    "data_date": "2026-07-07",
    "source": "auto",
    "source_url": "https://www.yuantaetfs.com/product/detail/0056/ratio"
  },
  {
    "etf_code": "006208",
    "etf_name": "富邦台50",
    "stock_code": "2330",
    "stock_name": "台積電",
    "weight": 52.1,
    "shares": 78600,
    "data_date": "",
    "source": "previous",
    "source_url": ""
  },
  {
    "etf_code": "006208",
    "etf_name": "富邦台50",
    "stock_code": "2317",
    "stock_name": "鴻海",
    "weight": 5.7,
    "shares": 40200,
    "data_date": "",
    "source": "previous",
    "source_url": ""
  },
  {
    "etf_code": "006208",
    "etf_name": "富邦台50",
    "stock_code": "2454",
    "stock_name": "聯發科",
    "weight": 4.6,
    "shares": 6200,
    "data_date": "",
    "source": "previous",
    "source_url": ""
  },
  {
    "etf_code": "00878",
    "etf_name": "國泰永續高股息",
    "stock_code": "2330",
    "stock_name": "台積電",
    "weight": 8.2,
    "shares": 88000,
    "data_date": "2026-07-07",
    "source": "csv",
    "source_url": "sources/holdings/00878.csv"
  },
  {
    "etf_code": "00878",
    "etf_name": "國泰永續高股息",
    "stock_code": "2317",
    "stock_name": "鴻海",
    "weight": 6.1,
    "shares": 56000,
    "data_date": "2026-07-07",
    "source": "csv",
    "source_url": "sources/holdings/00878.csv"
  },
  {
    "etf_code": "00878",
    "etf_name": "國泰永續高股息",
    "stock_code": "2454",
    "stock_name": "聯發科",
    "weight": 4.9,
    "shares": 12000,
    "data_date": "2026-07-07",
    "source": "csv",
    "source_url": "sources/holdings/00878.csv"
  },
  {
    "etf_code": "00919",
    "etf_name": "群益台灣精選高息",
    "stock_code": "2382",
    "stock_name": "廣達",
    "weight": 6.2,
    "shares": 45200,
    "data_date": "",
    "source": "previous",
    "source_url": ""
  },
  {
    "etf_code": "00919",
    "etf_name": "群益台灣精選高息",
    "stock_code": "3231",
    "stock_name": "緯創",
    "weight": 5.4,
    "shares": 76500,
    "data_date": "",
    "source": "previous",
    "source_url": ""
  },
  {
    "etf_code": "00919",
    "etf_name": "群益台灣精選高息",
    "stock_code": "2891",
    "stock_name": "中信金",
    "weight": 4.9,
    "shares": 132000,
    "data_date": "",
    "source": "previous",
    "source_url": ""
  },
  {
    "etf_code": "00929",
    "etf_name": "復華台灣科技優息",
    "stock_code": "2379",
    "stock_name": "瑞昱",
    "weight": 5.1,
    "shares": 9100,
    "data_date": "",
    "source": "previous",
    "source_url": ""
  },
  {
    "etf_code": "00929",
    "etf_name": "復華台灣科技優息",
    "stock_code": "3034",
    "stock_name": "聯詠",
    "weight": 4.8,
    "shares": 8200,
    "data_date": "",
    "source": "previous",
    "source_url": ""
  },
  {
    "etf_code": "00981A",
    "etf_name": "主動統一台股增長",
    "stock_code": "2330",
    "stock_name": "台積電",
    "weight": 28.4,
    "shares": 10600,
    "data_date": "",
    "source": "previous",
    "source_url": ""
  },
  {
    "etf_code": "00981A",
    "etf_name": "主動統一台股增長",
    "stock_code": "3661",
    "stock_name": "世芯-KY",
    "weight": 7.9,
    "shares": 860,
    "data_date": "",
    "source": "previous",
    "source_url": ""
  },
  {
    "etf_code": "00981A",
    "etf_name": "主動統一台股增長",
    "stock_code": "6669",
    "stock_name": "緯穎",
    "weight": 6.5,
    "shares": 1200,
    "data_date": "",
    "source": "previous",
    "source_url": ""
  },
  {
    "etf_code": "00982A",
    "etf_name": "主動群益台灣強棒",
    "stock_code": "2382",
    "stock_name": "廣達",
    "weight": 9.2,
    "shares": 8900,
    "data_date": "",
    "source": "previous",
    "source_url": ""
  },
  {
    "etf_code": "00982A",
    "etf_name": "主動群益台灣強棒",
    "stock_code": "3017",
    "stock_name": "奇鋐",
    "weight": 6.8,
    "shares": 3100,
    "data_date": "",
    "source": "previous",
    "source_url": ""
  }
]
